{
  "type": "FeatureCollection",
  "features": [
    {
      "type": "Feature",
      "geometry": {
        "type": "Point",
        "coordinates": [
          44.300381,
          39.702761,
          0
        ]
      },
      "properties": {
        "name": "Ararat / Urartu",
        "visibility": false,
        "open": "1",
        "styleUrl": "#landrepresentativepoint0",
        "icon-scale": 0.75,
        "icon": "https://maps.google.com/mapfiles/kml/paddle/wht-circle.png"
      }
    }
  ]
}
